copytrav/__init__.py
copytrav/data/one/data1.rst
copytrav/data/one/data1.txt
copytrav/data/two/data2.rst
copytrav/data/two/data2.txt
copytrav/data/two/even_more_data/data3.rst
copytrav/data/two/even_more_data/data3.txt
copytrav-0.0.5.dist-info/LICENSE
copytrav-0.0.5.dist-info/METADATA
copytrav-0.0.5.dist-info/WHEEL
copytrav-0.0.5.dist-info/top_level.txt
copytrav-0.0.5.dist-info/RECORD
